LICENSE
mercor_sdk/__init__.py
mercor_sdk/client.py
mercor_sdk/datatypes/__init__.py
mercor_sdk/datatypes/balance.py
mercor_sdk/datatypes/client.py
mercor_sdk/datatypes/status.py
mercor_sdk/datatypes/ticker.py
mercor_sdk/datatypes/trade.py
mercor_sdk/tokens.py
mercor_sdk-0.1.2.dist-info/LICENSE
mercor_sdk-0.1.2.dist-info/WHEEL
mercor_sdk-0.1.2.dist-info/METADATA
mercor_sdk-0.1.2.dist-info/RECORD
