Metadata-Version: 2.1
Name: mercor-sdk
Version: 0.1.2
Summary: Software development kit for the Mercor trading API
License: MIT
Author: Mercor Finance LLC
Requires-Python: >=3.7,<4.0
Classifier: License :: OSI Approved :: MIT License
Classifier: Programming Language :: Python :: 3
Classifier: Programming Language :: Python :: 3.7
Classifier: Programming Language :: Python :: 3.8
Classifier: Programming Language :: Python :: 3.9
Requires-Dist: backoff (>=1.11.1,<2.0.0)
Requires-Dist: eth-typing (>=2.2.2,<3.0.0)
Requires-Dist: pydantic (>=1.8.2,<2.0.0)
Requires-Dist: requests (>=2.26.0,<3.0.0)
